templator.py
templator/__main__.py
templator/__init__.py
templator/cli.py
templator/templates/__init__.py
templator/templates/html.py
templatory-0.6.1.dist-info/entry_points.txt
templatory-0.6.1.dist-info/metadata.json
templatory-0.6.1.dist-info/dependency_links.txt
templatory-0.6.1.dist-info/METADATA
templatory-0.6.1.dist-info/WHEEL
templatory-0.6.1.dist-info/pbr.json
templatory-0.6.1.dist-info/top_level.txt
templatory-0.6.1.dist-info/RECORD
templatory-0.6.1.dist-info/DESCRIPTION.rst
