Metadata-Version: 2.0
Name: templatory
Version: 0.6.1
Summary: Builds a *context* from arguments and renders one or more Jinja *templates* with
